bathyreq/__init__.py
bathyreq/request.py
bathyreq/sources/__init__.py
bathyreq/sources/blue_topo.py
bathyreq/sources/factory.py
bathyreq/sources/gebco.py
bathyreq/sources/ncei.py
bathyreq-1.1.0.dist-info/LICENSE
bathyreq-1.1.0.dist-info/METADATA
bathyreq-1.1.0.dist-info/WHEEL
bathyreq-1.1.0.dist-info/top_level.txt
bathyreq-1.1.0.dist-info/RECORD
