Metadata-Version: 2.1
Name: bathyreq
Version: 1.1.0
Summary: BathyReq: A Python package for querying public bathymetric data sources.
Author-email: William Jenkins <wjenkins@ucsd.edu>
License: MIT License
Project-URL: Homepage, https://neptuneprojects.github.io/BathyReq/
Project-URL: Repository, https://github.com/NeptuneProjects/BathyReq
Keywords: bathymetry,oceanography,data,query,download
Requires-Python: >=3.10
License-File: LICENSE
Requires-Dist: geopy
Requires-Dist: python-dotenv
Requires-Dist: rasterio
Requires-Dist: requests
Requires-Dist: scipy
